telemux/__init__.py
telemux/cleanup.py
telemux/cli.py
telemux/config.py
telemux/control.py
telemux/installer.py
telemux/listener.py
telemux/shell_functions.sh
telemux-1.0.9.dist-info/licenses/LICENSE
telemux-1.0.9.dist-info/METADATA
telemux-1.0.9.dist-info/WHEEL
telemux-1.0.9.dist-info/entry_points.txt
telemux-1.0.9.dist-info/top_level.txt
telemux-1.0.9.dist-info/RECORD
