Metadata-Version: 2.4
Name: telemux
Version: 1.0.9
Summary: Bidirectional Telegram integration for tmux sessions - monitor commands and interact with agents
Author-email: Marco Almazan <marco@example.com>
License: MIT
Project-URL: Homepage, https://github.com/malmazan/telemux
Project-URL: Repository, https://github.com/malmazan/telemux
Project-URL: Issues, https://github.com/malmazan/telemux/issues
Keywords: telegram,tmux,notifications,monitoring,agent,automation
Classifier: Development Status :: 4 - Beta
Classifier: Intended Audience :: Developers
Classifier: Intended Audience :: System Administrators
Classifier: License :: OSI Approved :: MIT License
Classifier: Operating System :: MacOS
Classifier: Operating System :: POSIX :: Linux
Classifier: Programming Language :: Python :: 3
Classifier: Programming Language :: Python :: 3.7
Classifier: Programming Language :: Python :: 3.8
Classifier: Programming Language :: Python :: 3.9
Classifier: Programming Language :: Python :: 3.10
Classifier: Programming Language :: Python :: 3.11
Classifier: Programming Language :: Python :: 3.12
Classifier: Topic :: Communications :: Chat
Classifier: Topic :: System :: Monitoring
Classifier: Topic :: System :: Systems Administration
Classifier: Topic :: Utilities
Requires-Python: >=3.7
License-File: LICENSE
Requires-Dist: requests<3.0.0,>=2.25.0
Provides-Extra: dev
Requires-Dist: pytest>=7.4.0; extra == "dev"
Requires-Dist: pytest-mock>=3.11.1; extra == "dev"
Requires-Dist: pytest-cov>=4.1.0; extra == "dev"
Requires-Dist: responses>=0.23.0; extra == "dev"
Dynamic: license-file
